README
setup.py
django_failedloginblocker.egg-info/PKG-INFO
django_failedloginblocker.egg-info/SOURCES.txt
django_failedloginblocker.egg-info/dependency_links.txt
django_failedloginblocker.egg-info/top_level.txt
failedloginblocker/__init__.py
failedloginblocker/admin.py
failedloginblocker/backends.py
failedloginblocker/decorators.py
failedloginblocker/exceptions.py
failedloginblocker/middleware.py
failedloginblocker/models.py
failedloginblocker/tests.py