Metadata-Version: 1.0
Name: django-failedloginblocker
Version: 1.0.1
Summary: UNKNOWN
Home-page: https://github.com/mysociety/django-failedloginblocker
Author: mySociety
Author-email: programmers@mysociety.org
License: BSD (3-Clause) License
Platform: UNKNOWN
